qrcodex/__init__.py
qrcodex/capacity.py
qrcodex/cli.py
qrcodex/encoder.py
qrcodex/encoding.py
qrcodex/error_correction.py
qrcodex/exceptions.py
qrcodex/generator.py
qrcodex/matrix.py
qrcodex/qr_algorithm.py
qrcodex/reed_solomon.py
qrcodex/utils.py
qrcodex-0.1.1.dist-info/licenses/LICENSE
qrcodex-0.1.1.dist-info/METADATA
qrcodex-0.1.1.dist-info/WHEEL
qrcodex-0.1.1.dist-info/top_level.txt
qrcodex-0.1.1.dist-info/RECORD
