Metadata-Version: 2.4
Name: qrcodex
Version: 0.1.1
Summary: An advanced QR code generator with multiple data type support
Home-page: https://github.com/GamingOP69/qrcodex
Author: GamingOP
Author-email: GamingOP <samratkafle36@gmail.com>
License-Expression: MIT
Project-URL: Homepage, https://github.com/GamingOP69/qrcodex
Project-URL: Repository, https://github.com/GamingOP69/qrcodex.git
Classifier: Development Status :: 3 - Alpha
Classifier: Intended Audience :: Developers
Classifier: Programming Language :: Python :: 3
Classifier: Programming Language :: Python :: 3.7
Classifier: Programming Language :: Python :: 3.8
Classifier: Programming Language :: Python :: 3.9
Classifier: Programming Language :: Python :: 3.10
Requires-Python: >=3.7
License-File: LICENSE
Requires-Dist: pillow>=9.0.0
Dynamic: author
Dynamic: home-page
Dynamic: license-file
Dynamic: requires-python
